Fictometer/__init__.py
Fictometer/fictometer.sav
Fictometer-0.2.5.dist-info/LICENSE
Fictometer-0.2.5.dist-info/METADATA
Fictometer-0.2.5.dist-info/WHEEL
Fictometer-0.2.5.dist-info/top_level.txt
Fictometer-0.2.5.dist-info/RECORD
