Metadata-Version: 2.1
Name: Fictometer
Version: 0.2.5
Summary: Classifies text as 'Fiction' or 'Non-Fiction'.
Author-email: Kushal Shah <atmabodha@gmail.com>
Project-URL: Homepage, https://bekushal.medium.com/fictometer-a-simple-and-explainable-algorithm-for-sentiment-analysis-31186d2a8c7e
Keywords: Fictometer,Fiction,Non-Fiction
Classifier: Programming Language :: Python :: 3
Classifier: License :: OSI Approved :: MIT License
Classifier: Operating System :: OS Independent
Requires-Python: >=3.11.9
License-File: LICENSE
Requires-Dist: nltk >=3.8.1
